packedtrie.py
packedtrie-0.1.0.dist-info/licenses/LICENSE
packedtrie-0.1.0.dist-info/METADATA
packedtrie-0.1.0.dist-info/WHEEL
packedtrie-0.1.0.dist-info/top_level.txt
packedtrie-0.1.0.dist-info/RECORD
