Metadata-Version: 2.4
Name: packedtrie
Version: 0.1.0
Summary: Flat-packed memory-efficient prefix trie
Author-email: VArgenti <viktor.silwer@gmail.com>
License: BSD 2-Clause License
Project-URL: Homepage, https://github.com/VArgenti/PackedTrie
Requires-Python: >=3.10
License-File: LICENSE
Dynamic: license-file
